boiga/__init__.py
boiga/compose.py
boiga/either.py
boiga/functor.py
boiga/maybe.py
boiga/monad.py
boiga/partial.py
boiga/py.typed
boiga/util.py
boiga-0.2.0.dist-info/LICENSE
boiga-0.2.0.dist-info/METADATA
boiga-0.2.0.dist-info/WHEEL
boiga-0.2.0.dist-info/top_level.txt
boiga-0.2.0.dist-info/RECORD
