Metadata-Version: 2.1
Name: boiga
Version: 0.2.0
Summary: Type-safe functional programming
Home-page: https://github.com/amarshall/boiga
Author: Andrew Marshall
License: MIT
Platform: UNKNOWN
Classifier: Development Status :: 2 - Pre-Alpha
Classifier: Intended Audience :: Developers
Classifier: License :: OSI Approved :: MIT License
Classifier: Operating System :: Unix
Classifier: Operating System :: POSIX
Classifier: Operating System :: Microsoft :: Windows
Classifier: Programming Language :: Python
Classifier: Programming Language :: Python :: 3
Classifier: Programming Language :: Python :: 3.6
Classifier: Programming Language :: Python :: 3.7
Classifier: Programming Language :: Python :: Implementation :: CPython
Classifier: Topic :: Utilities
Requires-Python: >= 3.6
Requires-Dist: typing-extensions (<4.0,>=3.6.6)
